<?xml version="1.0" encoding="utf-8"?>
<song xmlns="http://openlyrics.info/namespace/2009/song" version="0.8" createdIn="byHand 1.0" modifiedIn="byHand 1.0" modifiedDate="2019-06-01T00:00:00">
  <properties>
    <titles>
      <title>Hívők szent magasztos helye</title>
    </titles>
    <verseOrder>v1 v2 v3</verseOrder>
    <authors>
      <author type="music">Dr. Nettleton (1783-1844.)</author>
    </authors>
    <songbooks>
      <songbook name="Üdv- és adventi énekek" entry="12"/>
      <songbook name="Hitünk énekei" entry="397"/>
    </songbooks>
    <themes>
      <theme>Istentisztelethez: Megnyitó énekek</theme>
    </themes>
  </properties>
  <lyrics>
    <verse name="v1">
      <lines>Hívők szent magasztos helye,<br/>hol hozzád fohászunk száll,<br/>engedj mikor gyűlünk egybe,<br/>ott lennünk orcáidnál.<br/>Földiektől ha megválunk,<br/>örök léttől ihletve,<br/>magasztos békét találunk,<br/>lelkünk szomját tölti be.</lines>
    </verse>
    <verse name="v2">
      <lines>Angyalok karának vélve,<br/>ihlet hangját figyelem.<br/>Ha lerogytam búsan félve,<br/>újra felemel hitem.<br/>Földiektől ha megválunk,<br/>örök léttől ihletve,<br/>magasztos békét találunk,<br/>lelkünk szomját tölti be.</lines>
    </verse>
    <verse name="v3">
      <lines>S ha majdan végítéletre,<br/>Uram veled feljutok,<br/>minden bútól, gondtól mentve,<br/>zengjenek dicshimnuszok.<br/>Földiektől ha megválunk,<br/>örök léttől ihletve,<br/>magasztos békét találunk,<br/>lelkünk szomját tölti be.</lines>
    </verse>
  </lyrics>
</song>
