<?xml version='1.0' encoding='utf-8'?>
<song xmlns="http://openlyrics.info/namespace/2009/song" version="0.8" createdIn="byHand 1.0" modifiedIn="byHand 1.0" modifiedDate="2018-08-01T00:00:00">
  <properties>
    <titles>
      <title>A mélyből Hozzád száll szavam</title>
      <title>Go Down Moses</title>
    </titles>
    <authors>
      <author type="music">Spirituálé</author>
      <author type="words">Cselényi István Gábor</author>
    </authors>
    <verseOrder>v1 c1 v2 c1 v3 c1</verseOrder>
    <songbooks>
      <songbook name="Adj zengő éneket!" entry="3"/>
      <songbook name="Hozsánna énekes" entry="4"/>
    </songbooks>
  </properties>
  <lyrics>
    <verse name="v1">
      <lines>A mélyből Hozzád száll szavam,<br/>Krisztus, kegyelmezz!<br/>A bajban lelkem társtalan,<br/>Krisztus kegyelmezz!</lines>
    </verse>
    <verse name="c1">
      <lines>Segíts! Segíts!<br/>Ne hagyj! Ne hagyj!<br/>Nézd, rám tör a bűn már!<br/>Te adj! Te adj!<br/>Erőt! Erőt!<br/>Krisztus kegyelmezz!</lines>
    </verse>
    <verse name="v2">
      <lines>Ha ajkam vétett Ellened,<br/>Krisztus, kegyelmezz!<br/>A jó hírt zengjem csak Veled,<br/>Krisztus, kegyelmezz!</lines>
    </verse>
    <verse name="v3">
      <lines>Ha arcod fényét elfedem,<br/>Krisztus, kegyelmezz!<br/>Te újból szólíts, Istenem!<br/>Krisztus, kegyelmezz!</lines>
    </verse>
  </lyrics>
</song>
