<?xml version="1.0" encoding="utf-8"?>
<song xmlns="http://openlyrics.info/namespace/2009/song" version="0.8" createdIn="byHand 1.0" modifiedIn="byHand 1.0" modifiedDate="2018-08-01T00:00:00">
  <properties>
    <titles>
      <title>Sűrű sötét van mindenfelé</title>
    </titles>
    <verseOrder>v1 v2 v3 v4</verseOrder>
    <authors>
      <author type="music">Draskóczy László</author>
      <author type="words">Ecsedy Aladár</author>
    </authors>
    <songbooks>
      <songbook name="Adj zengő éneket!" entry="120"/>
    </songbooks>
  </properties>
  <lyrics>
    <verse name="v1">
      <lines>Sűrű sötét van mindenfelé,<br/>utat keresek az éjben.<br/>Sem csillagfény, sem reménysugár,<br/>árnyak suhannak az éjben.<br/>Remegő szívem Hozzád kiált:<br/>ó, Uram, halld meg imámat!<br/>Menekvés nincsen, nem is lehet,<br/>Uram, csak egyedül Nálad.</lines>
    </verse>
    <verse name="v2">
      <lines>Jézus, Te vagy a hajnali fény,<br/>Te vagy a nap ragyogása.<br/>Te vagy az Isten lénye maga,<br/>arcának tündöklő mása.<br/>És aki Téged már megtalált,<br/>szívében ott van a béke.<br/>Te lettél annak örökre már<br/>oltalma és menedéke.</lines>
    </verse>
    <verse name="v3">
      <lines>Nem vagyok más, csak üres edény,<br/>tölts meg hát Lelkeddel engem!<br/>Igédnek áldott, szent ereje<br/>munkálkodjék már énbennem!<br/>Rajtam keresztül áradj, Uram,<br/>szerte ragyogjon a fényed!<br/>Hogy én általam sok árva szív<br/>békéjét Benned meglelje.</lines>
    </verse>
    <verse name="v4">
      <lines>Amerre járok, merre kelek,<br/>Te légy, Uram, a vezérem!<br/>Hogy saját tervem, akaratom<br/>ne legyen többé énnékem!<br/>Ne éljek többé már soha én,<br/>Lelkeddel élj Te énbennem!<br/>Általlépve majd a gyöngykapun,<br/>Uram, engedj Hozzád mennem!</lines>
    </verse>
  </lyrics>
</song>
