<?xml version='1.0' encoding='utf-8'?>
<song xmlns="http://openlyrics.info/namespace/2009/song" version="0.8" createdIn="byHand 1.0" modifiedIn="byHand 1.0" modifiedDate="2013-08-01T00:00:00">
  <properties>
    <titles>
      <title>Mennyei Atyánk</title>
    </titles>
    <verseOrder>v1</verseOrder>
    <authors>
      <author type="music">Bob Fitts</author>
      <author type="words">Szilvási Ágota</author>
    </authors>
    <songbooks>
      <songbook name="Szent az Úr" entry="23"/>
    </songbooks>
  </properties>
  <lyrics>
    <verse name="v1">
      <lines>Mennyei Atyánk, hadd dicsérjünk.<br/>Hadd magasztaljuk Szent neved.<br/>Jöjjön el a Te országod minél előbb.<br/>A Te néped epedve vár Reád.<br/>Áldott légy, ó Felséges Isten,<br/>ki voltál, vagy és eljövend.<br/>Áldott légy ó Felséges Isten,<br/>uralkodj örökké.</lines>
    </verse>
  </lyrics>
</song>