<?xml version="1.0" encoding="utf-8"?>
<song xmlns="http://openlyrics.info/namespace/2009/song" version="0.8" createdIn="byHand 1.0" modifiedIn="byHand 1.0" modifiedDate="2016-08-01T00:00:00">
  <properties>
    <titles>
      <title>Én Jézusom, téged a szívem szeret</title>
    </titles>
    <verseOrder>v1 v2 v3 v4</verseOrder>
    <authors>
      <author type="music">Gordon Adoniram (1836-1895.)</author>
      <author type="words">Featherstone William</author>
    </authors>
    <songbooks>
      <songbook name="Hitünk énekei" entry="213"/>
    </songbooks>
    <themes>
      <theme>A keresztyén élet - Krisztus követése</theme>
      <theme>Bűnbocsánat</theme>
      <theme>Jézus Krisztus dicsérete</theme>
      <theme>Jézus Krisztus győzelme</theme>
      <theme>Jézus Krisztus öröm forrása</theme>
      <theme>Jézus Krisztus visszajövetele</theme>
      <theme>Megváltás</theme>
      <theme>Szabadítás</theme>
      <theme>Szeretet</theme>
    </themes>
  </properties>
  <lyrics>
    <verse name="v1">
      <lines>Én Jézusom, téged a szívem szeret,<br/>a bűntől te megmentél már engemet;<br/>én megmentőm, megtartóm, szabadítóm,<br/>ó! mily nagyon szeretlek, jó Megváltóm!</lines>
    </verse>
    <verse name="v2">
      <lines>Én Jézusom, téged a szívem szeret,<br/>te eltörléd véreddel bűneimet.<br/>És énértem haltál meg ama napon:<br/>ó! mily nagyon szeretlek, én Jézusom!</lines>
    </verse>
    <verse name="v3">
      <lines>Én Jézusom, téged a szívem szeret,<br/>és dicsérem míg élek, nagy erődet!<br/>Ha végórám eljön is, ezt kiáltom:<br/>ó! mily nagyon szeretlek, én Jézusom!</lines>
    </verse>
    <verse name="v4">
      <lines>Én Jézusom, téged a szívem úgy vár,<br/>mert ádvented dicsfénye tündököl már.<br/>És szárnyal majd énekem, zeng hálaszóm,<br/>ó! mily nagyon szeretlek, jó Megváltóm!</lines>
    </verse>
  </lyrics>
</song>
