<?xml version='1.0' encoding='utf-8'?>
<song xmlns="http://openlyrics.info/namespace/2009/song" version="0.8" createdIn="byHand 1.0" modifiedIn="byHand 1.0" modifiedDate="2018-04-01T00:00:00">
  <properties>
    <titles>
      <title>Dicsérd</title>
    </titles>
    <verseOrder>c1 c1 v1 b1 c2 c2 v2 b2 c2</verseOrder>
    <songbooks>
      <songbook name="Hozsánna énekes" entry="38"/>
    </songbooks>
  </properties>
  <lyrics>
    <verse name="c1">
      <lines>Dicsérd, dicsérd,<br/>dicsérjed Őt reggel,<br/>dicsérjed Őt este!<br/>Dicsérd, dicsérd,<br/>dicsérjed Őt szüntelen!</lines>
    </verse>
    <verse name="v1">
      <lines>Oly jó az Úrnak<br/>dicséretet énekelni,<br/>szeretem az Ő útját,<br/>oly jó néki zengedezni, örvendezni,<br/>ujjongni az Ő útján.</lines>
    </verse>
    <verse name="b1">
      <lines>Így Jézusomról szólni<br/>szívem mindig kész,<br/>szívem mindig kész,<br/>szívem mindig kész,<br/>Így Jézusomról szólni<br/>szívem mindig kész,<br/>Ő élet, erő békesség.</lines>
    </verse>
    <verse name="c2">
      <lines>Jézus, Jézus,<br/>néked zeng az ének,<br/>magasztalunk Téged.<br/>Jézus, Jézus,<br/>hála néked Megváltónk.</lines>
    </verse>
    <verse name="v2">
      <lines>Méltó a Bárány,<br/>Övé legyen minden erő,<br/>hatalom és bölcsesség.<br/>Áldott Bárány hódolattal énekelünk,<br/>Tied minden tisztesség.</lines>
    </verse>
    <verse name="b2">
      <lines>Így Jézusom terólad<br/>zeng az énekem,<br/>zeng az énekem,<br/>zeng az énekem.<br/>Így Jézusom terólad<br/>zeng az énekem,<br/>ó, dicsőség a Báránynak!</lines>
    </verse>
  </lyrics>
</song>
