<?xml version='1.0' encoding='utf-8'?>
<song xmlns="http://openlyrics.info/namespace/2009/song" version="0.8" createdIn="byHand 1.0" modifiedIn="byHand 1.0" modifiedDate="2018-04-01T00:00:00">
  <properties>
    <titles>
      <title>Hozsánna!</title>
    </titles>
    <verseOrder>v1 c1 v2 c1 v3 c1</verseOrder>
    <songbooks>
      <songbook name="Hozsánna énekes" entry="94"/>
    </songbooks>
  </properties>
  <lyrics>
    <verse name="v1">
      <lines>Hozsánna! Hozsánna!<br/>Hozsánna Dávid fiának!<br/>Hozsánna! Hozsánna!<br/>Hozsánna Dávid fiának!</lines>
    </verse>
    <verse name="c1">
      <lines>Hozzád száll énekünk,<br/>szívünkből szeretünk:<br/>nincs kőszikla senki más,<br/>csak te vagy a mi Istenünk!</lines>
    </verse>
    <verse name="v2">
      <lines>Dicsőség! Dicsőség!<br/>Dicsőség a feltámadott Úrnak!<br/>Dicsőség! Dicsőség!<br/>Dicsőség a feltámadott Úrnak!</lines>
    </verse>
    <verse name="v3">
      <lines>Jézus, Jézus,<br/>Isten Báránya.<br/>Jézus, Jézus,<br/>Isten Báránya.</lines>
    </verse>
  </lyrics>
</song>
