<?xml version='1.0' encoding='utf-8'?>
<song xmlns="http://openlyrics.info/namespace/2009/song" version="0.8" createdIn="byHand 1.0" modifiedIn="byHand 1.0" modifiedDate="2018-08-01T00:00:00">
  <properties>
    <titles>
      <title>Jövel, jövel Immánuel</title>
    </titles>
    <verseOrder>v1 v2 v3 v4 v5 v6</verseOrder>
    <authors>
      <author type="music">XV. századi gregorián dallam</author>
      <author type="translation" lang="hu">Szedő Dénes</author>
    </authors>
    <songbooks>
      <songbook name="Adj zengő éneket!" entry="68"/>
    </songbooks>
    <themes>
      <theme>Mt 1,23</theme>
    </themes>
  </properties>
  <lyrics>
    <verse name="v1">
      <lines>Jövel, jövel Immánuel!<br/>Csak téged áhít Izráel!<br/>És hozzád sóhajt untalan,<br/>mert Isten híján hontalan.<br/>Meglásd, meglásd, ó Izráel,<br/>hogy eljövend Immánuel.</lines>
    </verse>
    <verse name="v2">
      <lines>Jövel, ó Jessze vesszeje,<br/>és állj a Rossznak ellene!<br/>A mélyből, mely már eltemet,<br/>s a tűzből mentsd ki népedet!<br/>Meglásd, meglásd, ó Izráel,<br/>hogy eljövend Immánuel.</lines>
    </verse>
    <verse name="v3">
      <lines>Jövel, jövel, ó Napkelet,<br/>ím árva néped költöget.<br/>Törd át a sűrű éj ködét,<br/>és oszlasd gyászát szerteszét!<br/>Meglásd, meglásd, ó Izráel,<br/>hogy eljövend Immánuel.</lines>
    </verse>
    <verse name="v4">
      <lines>Jövel, ó, Dávid adta kulcs,<br/>hogy fényességes napra gyújts!<br/>A mennyországba tárj utat,<br/>és rekeszd el a poklokat!<br/>Meglásd, meglásd, ó Izráel,<br/>hogy eljövend Immánuel.</lines>
    </verse>
    <verse name="v5">
      <lines>Jövel, jövel, ó Adonáj,<br/>Ki Sínáj hegyről szólalál!<br/>Hogy törvényt lássál népeden,<br/>jöjj, fenségednek teljiben!<br/>Meglásd, meglásd, ó Izráel,<br/>hogy eljövend Immánuel.</lines>
    </verse>
    <verse name="v6" lang="la">
      <lines>Veni, veni Emmanuel!<br/>Captivum solve Israel!<br/>Qui gemit in exilio,<br/>Privatus Dei Filio.<br/>Gaude, gaude, Emmanuel<br/>Nascetur pro te, Israel.</lines>
    </verse>
  </lyrics>
</song>
