<?xml version="1.0" encoding="utf-8"?>
<song xmlns="http://openlyrics.info/namespace/2009/song" version="0.8" createdIn="byHand 1.0" modifiedIn="byHand 1.0" modifiedDate="2018-08-01T00:00:00">
  <properties>
    <titles>
      <title>Simuljon mindig</title>
    </titles>
    <verseOrder>v1 c1 v2 c1</verseOrder>
    <authors>
      <author type="music">Ír áldás</author>
    </authors>
    <songbooks>
      <songbook name="Adj zengő éneket!" entry="118"/>
    </songbooks>
  </properties>
  <lyrics>
    <verse name="v1">
      <lines>Simuljon mindig lábad elé jó út,<br/>fújjon csak a hátad mögül szél!<br/>Hulljon az eső lágyan földedre,<br/>melegítse arcodat a fény!</lines>
    </verse>
    <verse name="c1">
      <lines>És míg újra látjuk egymást,<br/>tartson téged tenyerén az Úr!<br/>És míg újra találkozunk,<br/>őrizzen meg tégedet az Úr!</lines>
    </verse>
    <verse name="v2">
      <lines>Várunk, míg újra láthatjuk egymást,<br/>Urunk mindenhol legyen velünk!<br/>Óvjon meg minket, békében éljünk,<br/>fényességgel fogja a kezünk!</lines>
    </verse>
  </lyrics>
</song>
