<?xml version='1.0' encoding='utf-8'?>
<song xmlns="http://openlyrics.info/namespace/2009/song" version="0.8" createdIn="byHand 1.0" modifiedIn="byHand 1.0" modifiedDate="2018-02-01T00:00:00">
  <properties>
    <titles>
      <title>Emberek vagy angyalok nyelvén</title>
    </titles>
    <verseOrder>v1 c1 v2 c1</verseOrder>
    <authors>
      <author type="music">Soproni János</author>
      <author type="words">Soproni János</author>
    </authors>
    <songbooks>
      <songbook name="Erőm és énekem az Úr" entry="34"/>
    </songbooks>
    <themes>
      <theme>1 Kor. 13</theme>
    </themes>
  </properties>
  <lyrics>
    <verse name="v1">
      <lines>Emberek vagy angyalok nyelvén ha szólok,<br/>de szeretni nem tudok,<br/>életem zengő érc vagy pengő cimbalom csak,<br/>és akkor semmi vagyok.</lines>
    </verse>
    <verse name="c1">
      <lines>Hit, remény, szeretet, e három közül<br/>a legnagyobb lett a szeretet,<br/>elfedez mindent, hisz és mindent remél,<br/>hadd töltse be most a szívemet.</lines>
    </verse>
    <verse name="v2">
      <lines>Lenne tudásom, vagyonom óriási,<br/>testem a tűzre adhatom,<br/>és hitem által a hegyek mozdulnának,<br/>én mégis semmi vagyok.</lines>
    </verse>
  </lyrics>
</song>
