<?xml version='1.0' encoding='utf-8'?>
<song xmlns="http://openlyrics.info/namespace/2009/song" version="0.8" createdIn="byHand 1.0" modifiedIn="byHand 1.0" modifiedDate="2019-04-01T00:00:00">
  <properties>
    <titles>
      <title>Áldjon meg téged</title>
    </titles>
    <verseOrder>v1</verseOrder>
    <songbooks>
      <songbook name="Dicsérem Neved 1" entry="2"/>
      <songbook name="Adj zengő éneket!" entry="10"/>
      <songbook name="Erőm és énekem az Úr" entry="4"/>
      <songbook name="Zuglói Adventista Gyülekezeti Énekeskönyv" entry="12"/>
    </songbooks>
    <themes>
      <theme>Köszöntés</theme>
      <theme>4Móz 6,24-26</theme>
    </themes>
  </properties>
  <lyrics>
    <verse name="v1">
      <lines>Áldjon meg téged, áldjon az Úr!<br/>Őrizzen téged, őrizzen ő!<br/>Orcáját mennyekből fordítsa reád,<br/>könyörüljön rajtad, könyörüljön rajtad!<br/>Adjon békességet!</lines>
    </verse>
  </lyrics>
</song>