<?xml version='1.0' encoding='utf-8'?>
<song xmlns="http://openlyrics.info/namespace/2009/song" version="0.8" createdIn="byHand 1.0" modifiedIn="byHand 1.0" modifiedDate="2018-02-01T00:00:00">
  <properties>
    <titles>
      <title>Áldott légy, Istenem</title>
    </titles>
    <authors>
      <author type="music">Kóczi József</author>
      <author type="words">Kóczi József</author>
    </authors>
    <verseOrder>v1 v2 v3</verseOrder>
    <songbooks>
      <songbook name="Hozsánna énekes" entry="19"/>
      <songbook name="Adj zengő éneket!" entry="12"/>
      <songbook name="Dicsérem Neved 1" entry="5"/>
    </songbooks>
  </properties>
  <lyrics>
    <verse name="v1">
      <lines>Áldott légy, Istenem, köszönöm neked,<br/>megtartod életem, köszönöm neked!<br/>Köszönöm a Golgotát, a Szent Fiad halálát!<br/>Köszönöm neked, köszönöm neked!<br/>Áldott légy, Istenem, köszönöm neked!</lines>
    </verse>
    <verse name="v2">
      <lines>Áldott légy, Istenem, köszönöm neked,<br/>megtartod életem, köszönöm neked!<br/>Köszönöm az életem, mindennapi kenyerem!<br/>Köszönöm neked, köszönöm neked!<br/>Áldott légy, Istenem, köszönöm neked!</lines>
    </verse>
    <verse name="v3">
      <lines>Áldott légy, Istenem, köszönöm neked,<br/>megtartod életem, köszönöm neked!<br/>Köszönöm az éjszakát, a ragyogó holdsugárt!<br/>Köszönöm neked, köszönöm neked!<br/>Áldott légy, Istenem, köszönöm neked!</lines>
    </verse>
  </lyrics>
</song>
